odoo/addons/maintenance_equipment_status/README.rst
odoo/addons/maintenance_equipment_status/__init__.py
odoo/addons/maintenance_equipment_status/__manifest__.py
odoo/addons/maintenance_equipment_status/i18n/es.po
odoo/addons/maintenance_equipment_status/i18n/maintenance_equipment_status.pot
odoo/addons/maintenance_equipment_status/models/__init__.py
odoo/addons/maintenance_equipment_status/models/maintenance_equipment.py
odoo/addons/maintenance_equipment_status/models/maintenance_equipment_status.py
odoo/addons/maintenance_equipment_status/readme/CONFIGURATION.rst
odoo/addons/maintenance_equipment_status/readme/CONTRIBUTORS.rst
odoo/addons/maintenance_equipment_status/readme/DESCRIPTION.rst
odoo/addons/maintenance_equipment_status/security/ir.model.access.csv
odoo/addons/maintenance_equipment_status/static/description/icon.png
odoo/addons/maintenance_equipment_status/static/description/index.html
odoo/addons/maintenance_equipment_status/tests/__init__.py
odoo/addons/maintenance_equipment_status/tests/test_maintenance_equipment_status.py
odoo/addons/maintenance_equipment_status/views/maintenance_equipment_status_views.xml
odoo/addons/maintenance_equipment_status/views/maintenance_equipment_views.xml
odoo13_addon_maintenance_equipment_status-13.0.1.0.1.dist-info/METADATA
odoo13_addon_maintenance_equipment_status-13.0.1.0.1.dist-info/WHEEL
odoo13_addon_maintenance_equipment_status-13.0.1.0.1.dist-info/top_level.txt
odoo13_addon_maintenance_equipment_status-13.0.1.0.1.dist-info/RECORD
