Metadata-Version: 2.1
Name: odoo13-addon-maintenance-equipment-status
Version: 13.0.1.0.1
Summary: Maintenance Equipment Status
Home-page: http://github.com/OCA/maintenance
Author: ForgeFlow, Odoo Community Association (OCA)
Author-email: support@odoo-community.org
License: LGPL-3
Platform: UNKNOWN
Classifier: Programming Language :: Python
Classifier: Framework :: Odoo
Classifier: License :: OSI Approved :: GNU Lesser General Public License v3 (LGPLv3)
Requires-Python: >=3.5
Requires-Dist: odoo13-addon-base-maintenance
Requires-Dist: odoo (<13.1dev,>=13.0a)
